{"nodes": [{"id": "c_users_mathieug_documents_github_ecotrack_src_helper_php", "label": "Helper.php", "file_type": "code", "source_file": "src/Helper.php", "source_location": "L1"}, {"id": "src_helper_error", "label": "error()", "file_type": "code", "source_file": "src/Helper.php", "source_location": "L3"}, {"id": "src_helper_old", "label": "old()", "file_type": "code", "source_file": "src/Helper.php", "source_location": "L7"}, {"id": "src_helper_escape", "label": "escape()", "file_type": "code", "source_file": "src/Helper.php", "source_location": "L11"}, {"id": "src_helper_slugify", "label": "slugify()", "file_type": "code", "source_file": "src/Helper.php", "source_location": "L15"}], "edges": [{"source": "c_users_mathieug_documents_github_ecotrack_src_helper_php", "target": "src_helper_error", "relation": "contains", "confidence": "EXTRACTED", "source_file": "src/Helper.php", "source_location": "L3", "weight": 1.0}, {"source": "c_users_mathieug_documents_github_ecotrack_src_helper_php", "target": "src_helper_old", "relation": "contains", "confidence": "EXTRACTED", "source_file": "src/Helper.php", "source_location": "L7", "weight": 1.0}, {"source": "c_users_mathieug_documents_github_ecotrack_src_helper_php", "target": "src_helper_escape", "relation": "contains", "confidence": "EXTRACTED", "source_file": "src/Helper.php", "source_location": "L11", "weight": 1.0}, {"source": "c_users_mathieug_documents_github_ecotrack_src_helper_php", "target": "src_helper_slugify", "relation": "contains", "confidence": "EXTRACTED", "source_file": "src/Helper.php", "source_location": "L15", "weight": 1.0}], "raw_calls": [{"caller_nid": "src_helper_error", "callee": "isset", "is_member_call": false, "source_file": "C:\\Users\\MathieuG\\Documents\\GitHub\\EcoTrack\\src\\Helper.php", "source_location": "L4", "receiver": null}, {"caller_nid": "src_helper_old", "callee": "isset", "is_member_call": false, "source_file": "C:\\Users\\MathieuG\\Documents\\GitHub\\EcoTrack\\src\\Helper.php", "source_location": "L8", "receiver": null}, {"caller_nid": "src_helper_escape", "callee": "stripslashes", "is_member_call": false, "source_file": "C:\\Users\\MathieuG\\Documents\\GitHub\\EcoTrack\\src\\Helper.php", "source_location": "L12", "receiver": null}, {"caller_nid": "src_helper_escape", "callee": "trim", "is_member_call": false, "source_file": "C:\\Users\\MathieuG\\Documents\\GitHub\\EcoTrack\\src\\Helper.php", "source_location": "L12", "receiver": null}, {"caller_nid": "src_helper_escape", "callee": "htmlspecialchars", "is_member_call": false, "source_file": "C:\\Users\\MathieuG\\Documents\\GitHub\\EcoTrack\\src\\Helper.php", "source_location": "L12", "receiver": null}, {"caller_nid": "src_helper_slugify", "callee": "preg_replace", "is_member_call": false, "source_file": "C:\\Users\\MathieuG\\Documents\\GitHub\\EcoTrack\\src\\Helper.php", "source_location": "L17", "receiver": null}, {"caller_nid": "src_helper_slugify", "callee": "iconv", "is_member_call": false, "source_file": "C:\\Users\\MathieuG\\Documents\\GitHub\\EcoTrack\\src\\Helper.php", "source_location": "L19", "receiver": null}, {"caller_nid": "src_helper_slugify", "callee": "preg_replace", "is_member_call": false, "source_file": "C:\\Users\\MathieuG\\Documents\\GitHub\\EcoTrack\\src\\Helper.php", "source_location": "L21", "receiver": null}, {"caller_nid": "src_helper_slugify", "callee": "trim", "is_member_call": false, "source_file": "C:\\Users\\MathieuG\\Documents\\GitHub\\EcoTrack\\src\\Helper.php", "source_location": "L23", "receiver": null}, {"caller_nid": "src_helper_slugify", "callee": "preg_replace", "is_member_call": false, "source_file": "C:\\Users\\MathieuG\\Documents\\GitHub\\EcoTrack\\src\\Helper.php", "source_location": "L25", "receiver": null}, {"caller_nid": "src_helper_slugify", "callee": "strtolower", "is_member_call": false, "source_file": "C:\\Users\\MathieuG\\Documents\\GitHub\\EcoTrack\\src\\Helper.php", "source_location": "L27", "receiver": null}, {"caller_nid": "src_helper_slugify", "callee": "empty", "is_member_call": false, "source_file": "C:\\Users\\MathieuG\\Documents\\GitHub\\EcoTrack\\src\\Helper.php", "source_location": "L28", "receiver": null}]}