{"nodes": [{"id": "c_users_mathieug_documents_github_ecotrack_src_models_defimanager_php", "label": "DefiManager.php", "file_type": "code", "source_file": "src/Models/DefiManager.php", "source_location": "L1"}, {"id": "models_defimanager_defimanager", "label": "DefiManager", "file_type": "code", "source_file": "src/Models/DefiManager.php", "source_location": "L5"}, {"id": "models_defimanager_defimanager_construct", "label": ".__construct()", "file_type": "code", "source_file": "src/Models/DefiManager.php", "source_location": "L20"}, {"id": "models_defimanager_defimanager_getlatestempreinte", "label": ".getLatestEmpreinte()", "file_type": "code", "source_file": "src/Models/DefiManager.php", "source_location": "L41"}, {"id": "models_defimanager_defimanager_getactivedefis", "label": ".getActiveDefis()", "file_type": "code", "source_file": "src/Models/DefiManager.php", "source_location": "L58"}, {"id": "models_defimanager_defimanager_getdailydefis", "label": ".getDailyDefis()", "file_type": "code", "source_file": "src/Models/DefiManager.php", "source_location": "L85"}, {"id": "models_defimanager_defimanager_getpostefocus", "label": ".getPosteFocus()", "file_type": "code", "source_file": "src/Models/DefiManager.php", "source_location": "L130"}, {"id": "models_defimanager_defimanager_getcompletedtodayids", "label": ".getCompletedTodayIds()", "file_type": "code", "source_file": "src/Models/DefiManager.php", "source_location": "L156"}, {"id": "models_defimanager_defimanager_getstats", "label": ".getStats()", "file_type": "code", "source_file": "src/Models/DefiManager.php", "source_location": "L170"}, {"id": "models_defimanager_defimanager_validatedefi", "label": ".validateDefi()", "file_type": "code", "source_file": "src/Models/DefiManager.php", "source_location": "L213"}, {"id": "models_defimanager_defimanager_computestreak", "label": ".computeStreak()", "file_type": "code", "source_file": "src/Models/DefiManager.php", "source_location": "L229"}], "edges": [{"source": "c_users_mathieug_documents_github_ecotrack_src_models_defimanager_php", "target": "models_defimanager_defimanager", "relation": "contains", "confidence": "EXTRACTED", "source_file": "src/Models/DefiManager.php", "source_location": "L5", "weight": 1.0}, {"source": "models_defimanager_defimanager", "target": "models_defimanager_defimanager_construct", "relation": "method", "confidence": "EXTRACTED", "source_file": "src/Models/DefiManager.php", "source_location": "L20", "weight": 1.0}, {"source": "models_defimanager_defimanager", "target": "models_defimanager_defimanager_getlatestempreinte", "relation": "method", "confidence": "EXTRACTED", "source_file": "src/Models/DefiManager.php", "source_location": "L41", "weight": 1.0}, {"source": "models_defimanager_defimanager", "target": "models_defimanager_defimanager_getactivedefis", "relation": "method", "confidence": "EXTRACTED", "source_file": "src/Models/DefiManager.php", "source_location": "L58", "weight": 1.0}, {"source": "models_defimanager_defimanager", "target": "models_defimanager_defimanager_getdailydefis", "relation": "method", "confidence": "EXTRACTED", "source_file": "src/Models/DefiManager.php", "source_location": "L85", "weight": 1.0}, {"source": "models_defimanager_defimanager", "target": "models_defimanager_defimanager_getpostefocus", "relation": "method", "confidence": "EXTRACTED", "source_file": "src/Models/DefiManager.php", "source_location": "L130", "weight": 1.0}, {"source": "models_defimanager_defimanager", "target": "models_defimanager_defimanager_getcompletedtodayids", "relation": "method", "confidence": "EXTRACTED", "source_file": "src/Models/DefiManager.php", "source_location": "L156", "weight": 1.0}, {"source": "models_defimanager_defimanager", "target": "models_defimanager_defimanager_getstats", "relation": "method", "confidence": "EXTRACTED", "source_file": "src/Models/DefiManager.php", "source_location": "L170", "weight": 1.0}, {"source": "models_defimanager_defimanager", "target": "models_defimanager_defimanager_validatedefi", "relation": "method", "confidence": "EXTRACTED", "source_file": "src/Models/DefiManager.php", "source_location": "L213", "weight": 1.0}, {"source": "models_defimanager_defimanager", "target": "models_defimanager_defimanager_computestreak", "relation": "method", "confidence": "EXTRACTED", "source_file": "src/Models/DefiManager.php", "source_location": "L229", "weight": 1.0}, {"source": "models_defimanager_defimanager_getdailydefis", "target": "models_defimanager_defimanager_getlatestempreinte", "relation": "calls", "context": "call", "confidence": "EXTRACTED", "source_file": "src/Models/DefiManager.php", "source_location": "L87", "weight": 1.0}, {"source": "models_defimanager_defimanager_getdailydefis", "target": "models_defimanager_defimanager_getactivedefis", "relation": "calls", "context": "call", "confidence": "EXTRACTED", "source_file": "src/Models/DefiManager.php", "source_location": "L88", "weight": 1.0}, {"source": "models_defimanager_defimanager_getpostefocus", "target": "models_defimanager_defimanager_getlatestempreinte", "relation": "calls", "context": "call", "confidence": "EXTRACTED", "source_file": "src/Models/DefiManager.php", "source_location": "L132", "weight": 1.0}, {"source": "models_defimanager_defimanager_getstats", "target": "models_defimanager_defimanager_computestreak", "relation": "calls", "context": "call", "confidence": "EXTRACTED", "source_file": "src/Models/DefiManager.php", "source_location": "L205", "weight": 1.0}], "raw_calls": [{"caller_nid": "models_defimanager_defimanager_construct", "callee": "die", "is_member_call": false, "source_file": "C:\\Users\\MathieuG\\Documents\\GitHub\\EcoTrack\\src\\Models\\DefiManager.php", "source_location": "L34", "receiver": null}, {"caller_nid": "models_defimanager_defimanager_construct", "callee": "getMessage", "is_member_call": true, "source_file": "C:\\Users\\MathieuG\\Documents\\GitHub\\EcoTrack\\src\\Models\\DefiManager.php", "source_location": "L34", "receiver": null}, {"caller_nid": "models_defimanager_defimanager_getlatestempreinte", "callee": "prepare", "is_member_call": true, "source_file": "C:\\Users\\MathieuG\\Documents\\GitHub\\EcoTrack\\src\\Models\\DefiManager.php", "source_location": "L43", "receiver": null}, {"caller_nid": "models_defimanager_defimanager_getlatestempreinte", "callee": "execute", "is_member_call": true, "source_file": "C:\\Users\\MathieuG\\Documents\\GitHub\\EcoTrack\\src\\Models\\DefiManager.php", "source_location": "L49", "receiver": null}, {"caller_nid": "models_defimanager_defimanager_getlatestempreinte", "callee": "fetch", "is_member_call": true, "source_file": "C:\\Users\\MathieuG\\Documents\\GitHub\\EcoTrack\\src\\Models\\DefiManager.php", "source_location": "L50", "receiver": null}, {"caller_nid": "models_defimanager_defimanager_getactivedefis", "callee": "fetchAll", "is_member_call": true, "source_file": "C:\\Users\\MathieuG\\Documents\\GitHub\\EcoTrack\\src\\Models\\DefiManager.php", "source_location": "L60", "receiver": null}, {"caller_nid": "models_defimanager_defimanager_getactivedefis", "callee": "query", "is_member_call": true, "source_file": "C:\\Users\\MathieuG\\Documents\\GitHub\\EcoTrack\\src\\Models\\DefiManager.php", "source_location": "L60", "receiver": null}, {"caller_nid": "models_defimanager_defimanager_getdailydefis", "callee": "arsort", "is_member_call": false, "source_file": "C:\\Users\\MathieuG\\Documents\\GitHub\\EcoTrack\\src\\Models\\DefiManager.php", "source_location": "L95", "receiver": null}, {"caller_nid": "models_defimanager_defimanager_getdailydefis", "callee": "array_keys", "is_member_call": false, "source_file": "C:\\Users\\MathieuG\\Documents\\GitHub\\EcoTrack\\src\\Models\\DefiManager.php", "source_location": "L96", "receiver": null}, {"caller_nid": "models_defimanager_defimanager_getdailydefis", "callee": "format", "is_member_call": true, "source_file": "C:\\Users\\MathieuG\\Documents\\GitHub\\EcoTrack\\src\\Models\\DefiManager.php", "source_location": "L99", "receiver": null}, {"caller_nid": "models_defimanager_defimanager_getdailydefis", "callee": "count", "is_member_call": false, "source_file": "C:\\Users\\MathieuG\\Documents\\GitHub\\EcoTrack\\src\\Models\\DefiManager.php", "source_location": "L104", "receiver": null}, {"caller_nid": "models_defimanager_defimanager_getdailydefis", "callee": "array_merge", "is_member_call": false, "source_file": "C:\\Users\\MathieuG\\Documents\\GitHub\\EcoTrack\\src\\Models\\DefiManager.php", "source_location": "L105", "receiver": null}, {"caller_nid": "models_defimanager_defimanager_getdailydefis", "callee": "array_slice", "is_member_call": false, "source_file": "C:\\Users\\MathieuG\\Documents\\GitHub\\EcoTrack\\src\\Models\\DefiManager.php", "source_location": "L106", "receiver": null}, {"caller_nid": "models_defimanager_defimanager_getdailydefis", "callee": "array_slice", "is_member_call": false, "source_file": "C:\\Users\\MathieuG\\Documents\\GitHub\\EcoTrack\\src\\Models\\DefiManager.php", "source_location": "L107", "receiver": null}, {"caller_nid": "models_defimanager_defimanager_getdailydefis", "callee": "count", "is_member_call": false, "source_file": "C:\\Users\\MathieuG\\Documents\\GitHub\\EcoTrack\\src\\Models\\DefiManager.php", "source_location": "L118", "receiver": null}, {"caller_nid": "models_defimanager_defimanager_getdailydefis", "callee": "count", "is_member_call": false, "source_file": "C:\\Users\\MathieuG\\Documents\\GitHub\\EcoTrack\\src\\Models\\DefiManager.php", "source_location": "L119", "receiver": null}, {"caller_nid": "models_defimanager_defimanager_getpostefocus", "callee": "arsort", "is_member_call": false, "source_file": "C:\\Users\\MathieuG\\Documents\\GitHub\\EcoTrack\\src\\Models\\DefiManager.php", "source_location": "L148", "receiver": null}, {"caller_nid": "models_defimanager_defimanager_getpostefocus", "callee": "array_key_first", "is_member_call": false, "source_file": "C:\\Users\\MathieuG\\Documents\\GitHub\\EcoTrack\\src\\Models\\DefiManager.php", "source_location": "L150", "receiver": null}, {"caller_nid": "models_defimanager_defimanager_getcompletedtodayids", "callee": "prepare", "is_member_call": true, "source_file": "C:\\Users\\MathieuG\\Documents\\GitHub\\EcoTrack\\src\\Models\\DefiManager.php", "source_location": "L158", "receiver": null}, {"caller_nid": "models_defimanager_defimanager_getcompletedtodayids", "callee": "execute", "is_member_call": true, "source_file": "C:\\Users\\MathieuG\\Documents\\GitHub\\EcoTrack\\src\\Models\\DefiManager.php", "source_location": "L162", "receiver": null}, {"caller_nid": "models_defimanager_defimanager_getcompletedtodayids", "callee": "date", "is_member_call": false, "source_file": "C:\\Users\\MathieuG\\Documents\\GitHub\\EcoTrack\\src\\Models\\DefiManager.php", "source_location": "L162", "receiver": null}, {"caller_nid": "models_defimanager_defimanager_getcompletedtodayids", "callee": "array_map", "is_member_call": false, "source_file": "C:\\Users\\MathieuG\\Documents\\GitHub\\EcoTrack\\src\\Models\\DefiManager.php", "source_location": "L164", "receiver": null}, {"caller_nid": "models_defimanager_defimanager_getcompletedtodayids", "callee": "array_column", "is_member_call": false, "source_file": "C:\\Users\\MathieuG\\Documents\\GitHub\\EcoTrack\\src\\Models\\DefiManager.php", "source_location": "L164", "receiver": null}, {"caller_nid": "models_defimanager_defimanager_getcompletedtodayids", "callee": "fetchAll", "is_member_call": true, "source_file": "C:\\Users\\MathieuG\\Documents\\GitHub\\EcoTrack\\src\\Models\\DefiManager.php", "source_location": "L164", "receiver": null}, {"caller_nid": "models_defimanager_defimanager_getstats", "callee": "prepare", "is_member_call": true, "source_file": "C:\\Users\\MathieuG\\Documents\\GitHub\\EcoTrack\\src\\Models\\DefiManager.php", "source_location": "L172", "receiver": null}, {"caller_nid": "models_defimanager_defimanager_getstats", "callee": "execute", "is_member_call": true, "source_file": "C:\\Users\\MathieuG\\Documents\\GitHub\\EcoTrack\\src\\Models\\DefiManager.php", "source_location": "L179", "receiver": null}, {"caller_nid": "models_defimanager_defimanager_getstats", "callee": "fetchAll", "is_member_call": true, "source_file": "C:\\Users\\MathieuG\\Documents\\GitHub\\EcoTrack\\src\\Models\\DefiManager.php", "source_location": "L180", "receiver": null}, {"caller_nid": "models_defimanager_defimanager_getstats", "callee": "date", "is_member_call": false, "source_file": "C:\\Users\\MathieuG\\Documents\\GitHub\\EcoTrack\\src\\Models\\DefiManager.php", "source_location": "L185", "receiver": null}, {"caller_nid": "models_defimanager_defimanager_getstats", "callee": "fetchColumn", "is_member_call": true, "source_file": "C:\\Users\\MathieuG\\Documents\\GitHub\\EcoTrack\\src\\Models\\DefiManager.php", "source_location": "L198", "receiver": null}, {"caller_nid": "models_defimanager_defimanager_getstats", "callee": "query", "is_member_call": true, "source_file": "C:\\Users\\MathieuG\\Documents\\GitHub\\EcoTrack\\src\\Models\\DefiManager.php", "source_location": "L198", "receiver": null}, {"caller_nid": "models_defimanager_defimanager_getstats", "callee": "count", "is_member_call": false, "source_file": "C:\\Users\\MathieuG\\Documents\\GitHub\\EcoTrack\\src\\Models\\DefiManager.php", "source_location": "L201", "receiver": null}, {"caller_nid": "models_defimanager_defimanager_getstats", "callee": "array_keys", "is_member_call": false, "source_file": "C:\\Users\\MathieuG\\Documents\\GitHub\\EcoTrack\\src\\Models\\DefiManager.php", "source_location": "L205", "receiver": null}, {"caller_nid": "models_defimanager_defimanager_validatedefi", "callee": "prepare", "is_member_call": true, "source_file": "C:\\Users\\MathieuG\\Documents\\GitHub\\EcoTrack\\src\\Models\\DefiManager.php", "source_location": "L215", "receiver": null}, {"caller_nid": "models_defimanager_defimanager_validatedefi", "callee": "execute", "is_member_call": true, "source_file": "C:\\Users\\MathieuG\\Documents\\GitHub\\EcoTrack\\src\\Models\\DefiManager.php", "source_location": "L219", "receiver": null}, {"caller_nid": "models_defimanager_defimanager_validatedefi", "callee": "date", "is_member_call": false, "source_file": "C:\\Users\\MathieuG\\Documents\\GitHub\\EcoTrack\\src\\Models\\DefiManager.php", "source_location": "L222", "receiver": null}, {"caller_nid": "models_defimanager_defimanager_computestreak", "callee": "array_flip", "is_member_call": false, "source_file": "C:\\Users\\MathieuG\\Documents\\GitHub\\EcoTrack\\src\\Models\\DefiManager.php", "source_location": "L235", "receiver": null}, {"caller_nid": "models_defimanager_defimanager_computestreak", "callee": "isset", "is_member_call": false, "source_file": "C:\\Users\\MathieuG\\Documents\\GitHub\\EcoTrack\\src\\Models\\DefiManager.php", "source_location": "L239", "receiver": null}, {"caller_nid": "models_defimanager_defimanager_computestreak", "callee": "format", "is_member_call": true, "source_file": "C:\\Users\\MathieuG\\Documents\\GitHub\\EcoTrack\\src\\Models\\DefiManager.php", "source_location": "L239", "receiver": null}, {"caller_nid": "models_defimanager_defimanager_computestreak", "callee": "modify", "is_member_call": true, "source_file": "C:\\Users\\MathieuG\\Documents\\GitHub\\EcoTrack\\src\\Models\\DefiManager.php", "source_location": "L240", "receiver": null}, {"caller_nid": "models_defimanager_defimanager_computestreak", "callee": "isset", "is_member_call": false, "source_file": "C:\\Users\\MathieuG\\Documents\\GitHub\\EcoTrack\\src\\Models\\DefiManager.php", "source_location": "L241", "receiver": null}, {"caller_nid": "models_defimanager_defimanager_computestreak", "callee": "format", "is_member_call": true, "source_file": "C:\\Users\\MathieuG\\Documents\\GitHub\\EcoTrack\\src\\Models\\DefiManager.php", "source_location": "L241", "receiver": null}, {"caller_nid": "models_defimanager_defimanager_computestreak", "callee": "isset", "is_member_call": false, "source_file": "C:\\Users\\MathieuG\\Documents\\GitHub\\EcoTrack\\src\\Models\\DefiManager.php", "source_location": "L247", "receiver": null}, {"caller_nid": "models_defimanager_defimanager_computestreak", "callee": "format", "is_member_call": true, "source_file": "C:\\Users\\MathieuG\\Documents\\GitHub\\EcoTrack\\src\\Models\\DefiManager.php", "source_location": "L247", "receiver": null}, {"caller_nid": "models_defimanager_defimanager_computestreak", "callee": "modify", "is_member_call": true, "source_file": "C:\\Users\\MathieuG\\Documents\\GitHub\\EcoTrack\\src\\Models\\DefiManager.php", "source_location": "L249", "receiver": null}]}